dcos/__init__.py
dcos/auth.py
dcos/cluster.py
dcos/cmds.py
dcos/config.py
dcos/constants.py
dcos/cosmos.py
dcos/errors.py
dcos/http.py
dcos/jsonitem.py
dcos/marathon.py
dcos/mesos.py
dcos/metronome.py
dcos/options.py
dcos/package.py
dcos/packagemanager.py
dcos/recordio.py
dcos/rpcclient.py
dcos/sse.py
dcos/ssh_util.py
dcos/subcommand.py
dcos/subprocess.py
dcos/util.py
dcos/data/config-schema/cluster.json
dcos/data/config-schema/core.json
dcos/data/config-schema/job.json
dcos/data/config-schema/marathon.json
dcos/data/config-schema/package.json
dcos/data/marathon/error.schema.json
dcos/security/__init__.py
dcos/security/iam.py
dcos/security/secrets.py
dcos_python-0.1.3.dist-info/METADATA
dcos_python-0.1.3.dist-info/RECORD
dcos_python-0.1.3.dist-info/WHEEL
dcos_python-0.1.3.dist-info/top_level.txt
