Metadata-Version: 2.1
Name: dcos-python
Version: 0.1.3
Summary: DCOS Python Libraries
Home-page: https://github.com/dirkjonker/dcos-python
Author: Dirk Jonker
Author-email: UNKNOWN
License: UNKNOWN
Keywords: mesos apache marathon mesosphere command datacenter
Platform: UNKNOWN
Classifier: Development Status :: 4 - Beta
Classifier: Intended Audience :: Developers
Classifier: Intended Audience :: Information Technology
Classifier: Topic :: Software Development :: User Interfaces
Classifier: License :: OSI Approved :: Apache Software License
Classifier: Programming Language :: Python :: 2.7
Classifier: Programming Language :: Python :: 3
Classifier: Programming Language :: Python :: 3.5
Classifier: Programming Language :: Python :: 3.6
Requires-Dist: jsonschema (<3.0,>=2.5)
Requires-Dist: pager (<4.0,>=3.3)
Requires-Dist: prettytable (<1.0,>=0.7)
Requires-Dist: PyJWT (==1.4.2)
Requires-Dist: pygments (<3.0,>=2.0)
Requires-Dist: requests (<3.0,>=2.6)
Requires-Dist: six (<2.0,>=1.9)
Requires-Dist: toml (<1.0,>=0.9)
Requires-Dist: sseclient (==0.0.19)
Requires-Dist: retrying (==1.3.3)
Requires-Dist: futures (<4.0,>=3.0); python_version=="2.7"
